sparql_api_codegen/__init__.py
sparql_api_codegen/__main__.py
sparql_api_codegen/generate_code.py
sparql_api_codegen/py.typed
sparql_api_codegen/settings.py
sparql_api_codegen/utils.py
sparql_api_codegen-0.0.1.dist-info/METADATA
sparql_api_codegen-0.0.1.dist-info/WHEEL
sparql_api_codegen-0.0.1.dist-info/entry_points.txt
sparql_api_codegen-0.0.1.dist-info/licenses/LICENSE.txt
sparql_api_codegen-0.0.1.dist-info/RECORD
