Metadata-Version: 2.4
Name: sparql-api-codegen
Version: 0.0.1
Summary: Automatically generate python API package from a SPARQL endpoint using its VoID descriptive metadata
Project-URL: Homepage, https://github.com/TRIPLE-CHIST-ERA/sparql-api-codegen
Project-URL: Documentation, https://github.com/TRIPLE-CHIST-ERA/sparql-api-codegen
Project-URL: History, https://github.com/TRIPLE-CHIST-ERA/sparql-api-codegen/releases
Project-URL: Tracker, https://github.com/TRIPLE-CHIST-ERA/sparql-api-codegen/issues
Project-URL: Source, https://github.com/TRIPLE-CHIST-ERA/sparql-api-codegen
Author-email: Vincent Emonet <vincent.emonet@sib.swiss>
Maintainer-email: Vincent Emonet <vincent.emonet@sib.swiss>
License: MIT License
License-File: LICENSE.txt
Keywords: Python,SPARQL
Classifier: License :: OSI Approved :: MIT License
Classifier: Operating System :: OS Independent
Classifier: Programming Language :: Python :: 3
Classifier: Programming Language :: Python :: 3.9
Classifier: Programming Language :: Python :: 3.10
Classifier: Programming Language :: Python :: 3.11
Classifier: Programming Language :: Python :: 3.12
Requires-Python: >=3.9
Requires-Dist: requests
Requires-Dist: typer>=0.12.0
Provides-Extra: test
Requires-Dist: mypy>=1.4.1; extra == 'test'
Requires-Dist: pip-tools; extra == 'test'
Requires-Dist: pre-commit; extra == 'test'
Requires-Dist: pytest-cov>=6.0.0; extra == 'test'
Requires-Dist: pytest>=8.3.3; extra == 'test'
Requires-Dist: types-requests; extra == 'test'
